number_checker/__init__.py
number_checker/checker.py
number_checker-0.1.0.dist-info/METADATA
number_checker-0.1.0.dist-info/WHEEL
number_checker-0.1.0.dist-info/top_level.txt
number_checker-0.1.0.dist-info/RECORD
