Metadata-Version: 2.2
Name: number_checker
Version: 0.1.0
Summary: A simple library to check if a number is 99
Home-page: https://github.com/yourusername/number_checker
Author: Your Name
Author-email: your.email@example.com
Classifier: Programming Language :: Python :: 3
Classifier: License :: OSI Approved :: MIT License
Classifier: Operating System :: OS Independent
Requires-Python: >=3.6
Dynamic: author
Dynamic: author-email
Dynamic: classifier
Dynamic: home-page
Dynamic: requires-python
Dynamic: summary
